{"cameraMode":{"drawMode":0,"name":"Shaded","section":"Shading Mode"},"sceneLighting":false,"audioPlay":false,"sceneViewState":{"m_AlwaysRefresh":false,"showFog":true,"showSkybox":false,"showFlares":true,"showImageEffects":true,"showParticleSystems":true,"showVisualEffectGraphs":true,"m_FxEnabled":true},"in2DMode":false,"pivot":{"x":-3.276062488555908,"y":1.1628036499023438,"z":-0.9344441890716553},"rotation":{"x":0.05171770602464676,"y":0.756489634513855,"z":-0.06026795133948326,"w":0.6491655111312866},"size":4.261585712432861,"orthographic":true}