{"cameraMode":{"drawMode":0,"name":"Shaded","section":"Shading Mode"},"sceneLighting":true,"audioPlay":false,"sceneViewState":{"m_AlwaysRefresh":false,"showFog":true,"showSkybox":true,"showFlares":true,"showImageEffects":true,"showParticleSystems":true,"showVisualEffectGraphs":true,"m_FxEnabled":true},"in2DMode":false,"pivot":{"x":0.3630542755126953,"y":3.03877592086792,"z":-5.258206367492676},"rotation":{"x":-0.14735956490039826,"y":-0.6226186752319336,"z":0.12128650397062302,"w":-0.7591242790222168},"size":2.5949745178222658,"orthographic":false}